Metadata-Version: 1.0
Name: bigausspy
Version: 0.1
Summary: Gaussian and Binomial distributions
Home-page: UNKNOWN
Author: Obinna Iheanachor
Author-email: datascientistobi@mail.com
License: UNKNOWN
Platform: UNKNOWN
